setup.py
passkeeper/__init__.py
passkeeper/core.py
passkeeper.egg-info/PKG-INFO
passkeeper.egg-info/SOURCES.txt
passkeeper.egg-info/dependency_links.txt
passkeeper.egg-info/entry_points.txt
passkeeper.egg-info/top_level.txt