Metadata-Version: 1.0
Name: passkeeper
Version: 1.1
Summary: keep your username and password
Home-page: https://github.com/diaohaha/passkeeper
Author: Gaoda
Author-email: 18363120101@163.com
License: BSD
Platform: any
